LICENSE
django_async_orm/.coverage
django_async_orm/__init__.py
django_async_orm/apps.py
django_async_orm/iter.py
django_async_orm/manager.py
django_async_orm/query.py
django_async_orm/utils.py
django_async_orm/wrappers.py
django_async_orm-0.1.12.dist-info/LICENSE
django_async_orm-0.1.12.dist-info/WHEEL
django_async_orm-0.1.12.dist-info/METADATA
django_async_orm-0.1.12.dist-info/RECORD
