Metadata-Version: 2.1
Name: django-async-orm
Version: 0.1.12
Summary: Bringing async capabilities to django ORM
Home-page: https://github.com/rednaks/django-async-orm
License: MIT
Keywords: django,async,orm
Author: SkanderBM
Author-email: skander.bmahmoud@gmail.com
Requires-Python: >=3.7,<4.0
Classifier: Development Status :: 3 - Alpha
Classifier: Framework :: Django
Classifier: License :: OSI Approved :: MIT License
Classifier: Operating System :: OS Independent
Classifier: Programming Language :: Python :: 3
Classifier: Programming Language :: Python :: 3.10
Classifier: Programming Language :: Python :: 3.7
Classifier: Programming Language :: Python :: 3.8
Classifier: Programming Language :: Python :: 3.9
Classifier: Topic :: Software Development :: Documentation
Classifier: Topic :: Software Development :: Libraries :: Python Modules
Classifier: Topic :: Software Development :: Quality Assurance
Project-URL: Repository, https://github.com/rednaks/django-async-orm
